{
  "$schema": "https://schema.management.azure.com/schemas/2015-01-01/deploymentParameters.json#",
  "contentVersion": "1.0.0.0",
  "parameters": {
    "hubName": {
      "value": "iothub-uniquestring"
    },
    "storageName": {
      "value": "storageuniquestring"
    },
    "appServiceName": {
      "value": "function-uniquestring"
    },
    "location": {
      "value": "East US"
    },
    "appServicePlanName": {
      "value": "appserviceplan-uniquestring"
    },
    "resourceGroupName": {
      "value": "labrg-uniquestring"
    },
    "apphostplan": {
      "value": "apphostplan-uniquestring"
    }
  }
}